{"cameraMode":{"drawMode":0,"name":"Shaded","section":"Shading Mode"},"sceneLighting":true,"audioPlay":false,"sceneViewState":{"m_AlwaysRefresh":false,"showFog":true,"showSkybox":true,"showFlares":true,"showImageEffects":true,"showParticleSystems":true,"showVisualEffectGraphs":true,"m_FxEnabled":true},"in2DMode":false,"pivot":{"x":543.52001953125,"y":36.11800003051758,"z":405.70001220703127},"rotation":{"x":0.05514383688569069,"y":-0.9436618089675903,"z":0.20498324930667878,"w":0.253863126039505},"size":5.6076765060424809,"orthographic":false}